setup.cfg
setup.py
eCB1/__init__.py
eCB1/eCB1.py
eCB1.egg-info/PKG-INFO
eCB1.egg-info/SOURCES.txt
eCB1.egg-info/dependency_links.txt
eCB1.egg-info/requires.txt
eCB1.egg-info/top_level.txt