Metadata-Version: 2.1
Name: eCB1
Version: 0.0.15
Summary: A library to communicate with the eCB1 Hardy Barth Smart Meter for Hardy Barth Wallboxes
Home-page: https://github.com/nilsmau/eCB1
Download-URL: https://pypi.org/project/eCB1/0.0.15/
Author: nilsmau
Author-email: nilsmau@hotmail.com
License: GPL
Classifier: Development Status :: 3 - Alpha
Classifier: Environment :: Other Environment
Classifier: Intended Audience :: Developers
Classifier: License :: Free for non-commercial use
Classifier: Operating System :: OS Independent
Classifier: Programming Language :: Python
Classifier: Programming Language :: Python :: 3
Classifier: Programming Language :: Python :: 3.1
Classifier: Programming Language :: Python :: 3.2
Classifier: Programming Language :: Python :: 3.3
Classifier: Programming Language :: Python :: 3.4
Classifier: Programming Language :: Python :: 3.5
Classifier: Programming Language :: Python :: 3.6
Classifier: Programming Language :: Python :: 3.7
Classifier: Topic :: Home Automation
Classifier: Topic :: Software Development :: Libraries :: Python Modules
